{
    "8636013605": {
        "name": "Satyam",
        "username": null,
        "courses": [],
        "verified": true
    },
    "1236905570": {
        "name": "Yesman",
        "username": "Thatman099",
        "courses": [],
        "verified": true
    },
    "6586877310": {
        "name": "Namit",
        "username": null,
        "phone": "919532216702",
        "courses": [],
        "verified": true
    },
    "7209486623": {
        "name": "Professor \ud83e\udd7c",
        "username": "Csevala",
        "courses": [],
        "verified": true
    },
    "1308571847": {
        "name": "Suchit",
        "username": null,
        "phone": "919335146032",
        "verified": true,
        "courses": []
    },
    "1096104154": {
        "name": "Y S",
        "username": null,
        "courses": [],
        "verified": true
    }
}